geocodefarm/__init__.py
geocodefarm-4.0.dist-info/licenses/LICENSE
geocodefarm-4.0.dist-info/METADATA
geocodefarm-4.0.dist-info/WHEEL
geocodefarm-4.0.dist-info/top_level.txt
geocodefarm-4.0.dist-info/RECORD
