Metadata-Version: 2.4
Name: geocodefarm
Version: 4.0
Summary: A lightweight Geocode.Farm API client for Python
Home-page: https://github.com/geocodefarm/geocodefarm-py
Author: Geocode.Farm
License: Unlicense
Classifier: Programming Language :: Python :: 3
Classifier: Operating System :: OS Independent
Requires-Python: >=3.7
License-File: LICENSE
Dynamic: license-file
